{
    "title": "B. R. Harne College of Engineering and Technology: Admission 2024, Cutoff, Courses, Fees, Placements, Rankings",
    "meta_description": "B. R. Harne College of Engineering and Technology Admission 2024 is open for various degree programs based on MHT CET entrance exams and Maharashtra CAP Counselling. Check latest updates and news on B. R. Harne College of Engineering and TechnologyAdmission 2024, Cutoff, Courses, Fees, Eligibility, and Admission Process",
    "keywords": "B. R. Harne College of Engineering and Technology, B. R. Harne College of Engineering and Technology Admission 2024, B. R. Harne College of Engineering and Technology B.Tech Admission 2024, B. R. Harne College of Engineering and Technology Cutoff 2024, B. R. Harne College of Engineering and Technology Courses Admission 2024, B. R. Harne College of Engineering and Technology Cutoff, B. R. Harne College of Engineering and Technology Fees, B. R. Harne College of Engineering and Technology Admission Cutoff 2024, How much rank to get admission in B. R. Harne College of Engineering and Technology, B. R. Harne College of Engineering and Technology Admission Updates",
    "basic_info": [],
    "structured_data": [],
    "faqs": [],
    "Section": {
        "name": "About BRHCET",
        "description": "B. R. Harne College of Engineering and Technology (BRHCET) was established in 2011 by Jai Shri Siddhivinayak Foundation. It is committed to impart quality education & training leading to various professional degrees and aims to be a global Institution through continual improvement. The Campus is spread over 11.7 Acres of Land with beautiful building coming up. It is situated at Thane, Mumbai. It offers under graduate and post graduate Engineering courses, MCA and MBA.\nDepartment\nFacilities\nLibrary\nThe Library is well equipped with modem facilities and resources in the forms of CDROMs, DVD-ROM, online databases, micro-documents, video cassettes, books, journals, theses, reports, etc.\nTotal No. of Volumes\n5400\nTotal No. of Titles\n647\nNational Periodicals\n33\nInternational periodicals\n15\nCD Collection (Text books & Magazines)\n312\nNews Papers\n11\nE-Journal\n01\nDELNET\n01"
    },
    "BRHCET Fees & Eligibility": [
        {
            "Course": "BE7  Courses",
            "Fees": "₹3.2 Lakhs (Total Fees)",
            "Eligibility": "10+2",
            "Application Date": "16 Jan - 28 Jul 2024",
            "Action": "Apply Now"
        },
        {
            "Course": "Polytechnic2  Courses",
            "Fees": "₹36,000 - 44,000 (1st Year Fees)",
            "Eligibility": "10th Pass",
            "Application Date": "-",
            "Action": "Apply Now"
        },
        {
            "Course": "ME2  Courses",
            "Fees": "₹1.66 Lakhs (Total Fees)",
            "Eligibility": "Pass in Graduation",
            "Application Date": "9 July - 29 Jul 2024",
            "Action": "Apply Now"
        }
    ],
    "Important Events": [
        {
            "Events": "JEE Main 2025 Registration (Session - 1)",
            "Dates": "OngoingNov 01, 2024 - Dec 04, 2024"
        },
        {
            "Events": "JEE Main 2025 Admit Card (Session - 1)",
            "Dates": "TentativeJan 17, 2025"
        },
        {
            "Events": "JEE Main 2025 Exam Date (Session - 1)",
            "Dates": "Jan 24, 2025 - Jan 31, 2025"
        },
        {
            "Events": "JEE Main 2025 Result (Session - 1)",
            "Dates": "TentativeFeb 13, 2025"
        },
        {
            "Events": "MHT CET Registration Timeline",
            "Dates": "TentativeJan 16, 2025 - Mar 15, 2025"
        },
        {
            "Events": "MHT CET (PCB) Admit Card Date",
            "Dates": "TentativeApr 13, 2025"
        },
        {
            "Events": "MHT CET (PCM) Admit Card Date",
            "Dates": "TentativeApr 19, 2025"
        },
        {
            "Events": "MHT CET Exam Date",
            "Dates": "TentativeApr 22, 2025 - May 17, 2025"
        },
        {
            "Events": "MHT CET Result Date",
            "Dates": "TentativeJun 16, 2025"
        },
        {
            "Events": "JEE-Main counselling",
            "Dates": "Jun 10, 2025 - Jun 18, 2025"
        }
    ],
    "Expired Events": [
        {
            "Events": "Last Date for Non-CAP Round Admissions  [MAHCET - B.Tech]",
            "Dates": "Oct 23, 2024"
        },
        {
            "Events": "Last Date for Uploading Data Non-CAP Round [MAHCET - B.Tech]",
            "Dates": "Oct 23, 2024"
        },
        {
            "Events": "Non-CAP Round Registration Date [MAHCET - B.Tech]",
            "Dates": "Oct 01, 2024"
        }
    ],
    "BRHCET, MHT CET Cutoff 2024": [
        {
            "Courses": "BE Computer Engineering",
            "Round 1": "70.25",
            "Round 2": "54.18",
            "Round 3": "71.71"
        },
        {
            "Courses": "BE Computer Science and Engineering (Artificial Intelligence and Machine)",
            "Round 1": "60.62",
            "Round 2": "39.05",
            "Round 3": "66.19"
        },
        {
            "Courses": "BE Mechanical Engineering",
            "Round 1": "40.11",
            "Round 2": "6.31",
            "Round 3": "-"
        }
    ]
}